{"frames": {

"explosion/1/frame1.png":
{
	"frame": {"x":8,"y":32,"w":8,"h":8},
	"rotated": false,
	"trimmed": false,
	"spriteSourceSize": {"x":0,"y":0,"w":8,"h":8},
	"sourceSize": {"w":8,"h":8}
},
"explosion/1/frame2.png":
{
	"frame": {"x":24,"y":32,"w":8,"h":8},
	"rotated": false,
	"trimmed": false,
	"spriteSourceSize": {"x":0,"y":0,"w":8,"h":8},
	"sourceSize": {"w":8,"h":8}
},
"explosion/1/frame3.png":
{
	"frame": {"x":0,"y":40,"w":8,"h":8},
	"rotated": false,
	"trimmed": false,
	"spriteSourceSize": {"x":0,"y":0,"w":8,"h":8},
	"sourceSize": {"w":8,"h":8}
},
"explosion/1/frame4.png":
{
	"frame": {"x":16,"y":32,"w":8,"h":8},
	"rotated": false,
	"trimmed": false,
	"spriteSourceSize": {"x":0,"y":0,"w":8,"h":8},
	"sourceSize": {"w":8,"h":8}
},
"explosion/1/frame5.png":
{
	"frame": {"x":0,"y":24,"w":8,"h":8},
	"rotated": false,
	"trimmed": false,
	"spriteSourceSize": {"x":0,"y":0,"w":8,"h":8},
	"sourceSize": {"w":8,"h":8}
},
"explosion/1/frame6.png":
{
	"frame": {"x":8,"y":24,"w":8,"h":8},
	"rotated": false,
	"trimmed": false,
	"spriteSourceSize": {"x":0,"y":0,"w":8,"h":8},
	"sourceSize": {"w":8,"h":8}
},
"explosion/1/frame7.png":
{
	"frame": {"x":24,"y":24,"w":8,"h":8},
	"rotated": false,
	"trimmed": false,
	"spriteSourceSize": {"x":0,"y":0,"w":8,"h":8},
	"sourceSize": {"w":8,"h":8}
},
"explosion/1/frame8.png":
{
	"frame": {"x":0,"y":32,"w":8,"h":8},
	"rotated": false,
	"trimmed": false,
	"spriteSourceSize": {"x":0,"y":0,"w":8,"h":8},
	"sourceSize": {"w":8,"h":8}
},
"explosion/1/frame9.png":
{
	"frame": {"x":16,"y":24,"w":8,"h":8},
	"rotated": false,
	"trimmed": false,
	"spriteSourceSize": {"x":0,"y":0,"w":8,"h":8},
	"sourceSize": {"w":8,"h":8}
},
"explosion/2/frame1.png":
{
	"frame": {"x":0,"y":168,"w":16,"h":16},
	"rotated": false,
	"trimmed": false,
	"spriteSourceSize": {"x":0,"y":0,"w":16,"h":16},
	"sourceSize": {"w":16,"h":16}
},
"explosion/2/frame2.png":
{
	"frame": {"x":0,"y":216,"w":16,"h":16},
	"rotated": false,
	"trimmed": false,
	"spriteSourceSize": {"x":0,"y":0,"w":16,"h":16},
	"sourceSize": {"w":16,"h":16}
},
"explosion/2/frame3.png":
{
	"frame": {"x":0,"y":136,"w":16,"h":16},
	"rotated": false,
	"trimmed": false,
	"spriteSourceSize": {"x":0,"y":0,"w":16,"h":16},
	"sourceSize": {"w":16,"h":16}
},
"explosion/2/frame4.png":
{
	"frame": {"x":16,"y":200,"w":16,"h":16},
	"rotated": false,
	"trimmed": false,
	"spriteSourceSize": {"x":0,"y":0,"w":16,"h":16},
	"sourceSize": {"w":16,"h":16}
},
"explosion/2/frame5.png":
{
	"frame": {"x":16,"y":184,"w":16,"h":16},
	"rotated": false,
	"trimmed": false,
	"spriteSourceSize": {"x":0,"y":0,"w":16,"h":16},
	"sourceSize": {"w":16,"h":16}
},
"explosion/2/frame6.png":
{
	"frame": {"x":0,"y":152,"w":16,"h":16},
	"rotated": false,
	"trimmed": false,
	"spriteSourceSize": {"x":0,"y":0,"w":16,"h":16},
	"sourceSize": {"w":16,"h":16}
},
"explosion/2/frame7.png":
{
	"frame": {"x":16,"y":104,"w":16,"h":16},
	"rotated": false,
	"trimmed": false,
	"spriteSourceSize": {"x":0,"y":0,"w":16,"h":16},
	"sourceSize": {"w":16,"h":16}
},
"explosion/2/frame8.png":
{
	"frame": {"x":0,"y":72,"w":16,"h":16},
	"rotated": false,
	"trimmed": false,
	"spriteSourceSize": {"x":0,"y":0,"w":16,"h":16},
	"sourceSize": {"w":16,"h":16}
},
"explosion/2/frame9.png":
{
	"frame": {"x":16,"y":56,"w":16,"h":16},
	"rotated": false,
	"trimmed": false,
	"spriteSourceSize": {"x":0,"y":0,"w":16,"h":16},
	"sourceSize": {"w":16,"h":16}
},
"explosion/2/frame10.png":
{
	"frame": {"x":16,"y":168,"w":16,"h":16},
	"rotated": false,
	"trimmed": false,
	"spriteSourceSize": {"x":0,"y":0,"w":16,"h":16},
	"sourceSize": {"w":16,"h":16}
},
"explosion/2/frame11.png":
{
	"frame": {"x":16,"y":152,"w":16,"h":16},
	"rotated": false,
	"trimmed": false,
	"spriteSourceSize": {"x":0,"y":0,"w":16,"h":16},
	"sourceSize": {"w":16,"h":16}
},
"explosion/2/frame12.png":
{
	"frame": {"x":16,"y":136,"w":16,"h":16},
	"rotated": false,
	"trimmed": false,
	"spriteSourceSize": {"x":0,"y":0,"w":16,"h":16},
	"sourceSize": {"w":16,"h":16}
},
"explosion/2/frame13.png":
{
	"frame": {"x":0,"y":184,"w":16,"h":16},
	"rotated": false,
	"trimmed": false,
	"spriteSourceSize": {"x":0,"y":0,"w":16,"h":16},
	"sourceSize": {"w":16,"h":16}
},
"explosion/2/frame14.png":
{
	"frame": {"x":0,"y":200,"w":16,"h":16},
	"rotated": false,
	"trimmed": false,
	"spriteSourceSize": {"x":0,"y":0,"w":16,"h":16},
	"sourceSize": {"w":16,"h":16}
},
"explosion/3/frame1.png":
{
	"frame": {"x":16,"y":216,"w":16,"h":16},
	"rotated": false,
	"trimmed": false,
	"spriteSourceSize": {"x":0,"y":0,"w":16,"h":16},
	"sourceSize": {"w":16,"h":16}
},
"explosion/3/frame2.png":
{
	"frame": {"x":0,"y":344,"w":16,"h":16},
	"rotated": false,
	"trimmed": false,
	"spriteSourceSize": {"x":0,"y":0,"w":16,"h":16},
	"sourceSize": {"w":16,"h":16}
},
"explosion/3/frame3.png":
{
	"frame": {"x":16,"y":312,"w":16,"h":16},
	"rotated": false,
	"trimmed": false,
	"spriteSourceSize": {"x":0,"y":0,"w":16,"h":16},
	"sourceSize": {"w":16,"h":16}
},
"explosion/3/frame4.png":
{
	"frame": {"x":0,"y":296,"w":16,"h":16},
	"rotated": false,
	"trimmed": false,
	"spriteSourceSize": {"x":0,"y":0,"w":16,"h":16},
	"sourceSize": {"w":16,"h":16}
},
"explosion/3/frame5.png":
{
	"frame": {"x":16,"y":232,"w":16,"h":16},
	"rotated": false,
	"trimmed": false,
	"spriteSourceSize": {"x":0,"y":0,"w":16,"h":16},
	"sourceSize": {"w":16,"h":16}
},
"explosion/3/frame6.png":
{
	"frame": {"x":0,"y":248,"w":16,"h":16},
	"rotated": false,
	"trimmed": false,
	"spriteSourceSize": {"x":0,"y":0,"w":16,"h":16},
	"sourceSize": {"w":16,"h":16}
},
"explosion/3/frame7.png":
{
	"frame": {"x":0,"y":264,"w":16,"h":16},
	"rotated": false,
	"trimmed": false,
	"spriteSourceSize": {"x":0,"y":0,"w":16,"h":16},
	"sourceSize": {"w":16,"h":16}
},
"explosion/3/frame8.png":
{
	"frame": {"x":16,"y":280,"w":16,"h":16},
	"rotated": false,
	"trimmed": false,
	"spriteSourceSize": {"x":0,"y":0,"w":16,"h":16},
	"sourceSize": {"w":16,"h":16}
},
"explosion/3/frame9.png":
{
	"frame": {"x":16,"y":264,"w":16,"h":16},
	"rotated": false,
	"trimmed": false,
	"spriteSourceSize": {"x":0,"y":0,"w":16,"h":16},
	"sourceSize": {"w":16,"h":16}
},
"explosion/3/frame10.png":
{
	"frame": {"x":16,"y":296,"w":16,"h":16},
	"rotated": false,
	"trimmed": false,
	"spriteSourceSize": {"x":0,"y":0,"w":16,"h":16},
	"sourceSize": {"w":16,"h":16}
},
"explosion/3/frame11.png":
{
	"frame": {"x":0,"y":312,"w":16,"h":16},
	"rotated": false,
	"trimmed": false,
	"spriteSourceSize": {"x":0,"y":0,"w":16,"h":16},
	"sourceSize": {"w":16,"h":16}
},
"explosion/3/frame12.png":
{
	"frame": {"x":0,"y":328,"w":16,"h":16},
	"rotated": false,
	"trimmed": false,
	"spriteSourceSize": {"x":0,"y":0,"w":16,"h":16},
	"sourceSize": {"w":16,"h":16}
},
"explosion/3/frame13.png":
{
	"frame": {"x":16,"y":344,"w":16,"h":16},
	"rotated": false,
	"trimmed": false,
	"spriteSourceSize": {"x":0,"y":0,"w":16,"h":16},
	"sourceSize": {"w":16,"h":16}
},
"explosion/3/frame14.png":
{
	"frame": {"x":16,"y":328,"w":16,"h":16},
	"rotated": false,
	"trimmed": false,
	"spriteSourceSize": {"x":0,"y":0,"w":16,"h":16},
	"sourceSize": {"w":16,"h":16}
},
"explosion/4/frame1.png":
{
	"frame": {"x":0,"y":280,"w":16,"h":16},
	"rotated": false,
	"trimmed": false,
	"spriteSourceSize": {"x":0,"y":0,"w":16,"h":16},
	"sourceSize": {"w":16,"h":16}
},
"explosion/4/frame2.png":
{
	"frame": {"x":0,"y":360,"w":16,"h":16},
	"rotated": false,
	"trimmed": false,
	"spriteSourceSize": {"x":0,"y":0,"w":16,"h":16},
	"sourceSize": {"w":16,"h":16}
},
"explosion/4/frame3.png":
{
	"frame": {"x":16,"y":376,"w":16,"h":16},
	"rotated": false,
	"trimmed": false,
	"spriteSourceSize": {"x":0,"y":0,"w":16,"h":16},
	"sourceSize": {"w":16,"h":16}
},
"explosion/4/frame4.png":
{
	"frame": {"x":16,"y":424,"w":16,"h":16},
	"rotated": false,
	"trimmed": false,
	"spriteSourceSize": {"x":0,"y":0,"w":16,"h":16},
	"sourceSize": {"w":16,"h":16}
},
"explosion/4/frame5.png":
{
	"frame": {"x":0,"y":440,"w":16,"h":16},
	"rotated": false,
	"trimmed": false,
	"spriteSourceSize": {"x":0,"y":0,"w":16,"h":16},
	"sourceSize": {"w":16,"h":16}
},
"explosion/4/frame6.png":
{
	"frame": {"x":0,"y":456,"w":16,"h":16},
	"rotated": false,
	"trimmed": false,
	"spriteSourceSize": {"x":0,"y":0,"w":16,"h":16},
	"sourceSize": {"w":16,"h":16}
},
"explosion/4/frame7.png":
{
	"frame": {"x":16,"y":456,"w":16,"h":16},
	"rotated": false,
	"trimmed": false,
	"spriteSourceSize": {"x":0,"y":0,"w":16,"h":16},
	"sourceSize": {"w":16,"h":16}
},
"explosion/4/frame8.png":
{
	"frame": {"x":16,"y":472,"w":16,"h":16},
	"rotated": false,
	"trimmed": false,
	"spriteSourceSize": {"x":0,"y":0,"w":16,"h":16},
	"sourceSize": {"w":16,"h":16}
},
"explosion/4/frame9.png":
{
	"frame": {"x":0,"y":488,"w":16,"h":16},
	"rotated": false,
	"trimmed": false,
	"spriteSourceSize": {"x":0,"y":0,"w":16,"h":16},
	"sourceSize": {"w":16,"h":16}
},
"explosion/5/frame1.png":
{
	"frame": {"x":0,"y":472,"w":16,"h":16},
	"rotated": false,
	"trimmed": false,
	"spriteSourceSize": {"x":0,"y":0,"w":16,"h":16},
	"sourceSize": {"w":16,"h":16}
},
"explosion/5/frame2.png":
{
	"frame": {"x":16,"y":440,"w":16,"h":16},
	"rotated": false,
	"trimmed": false,
	"spriteSourceSize": {"x":0,"y":0,"w":16,"h":16},
	"sourceSize": {"w":16,"h":16}
},
"explosion/5/frame3.png":
{
	"frame": {"x":0,"y":424,"w":16,"h":16},
	"rotated": false,
	"trimmed": false,
	"spriteSourceSize": {"x":0,"y":0,"w":16,"h":16},
	"sourceSize": {"w":16,"h":16}
},
"explosion/5/frame4.png":
{
	"frame": {"x":16,"y":360,"w":16,"h":16},
	"rotated": false,
	"trimmed": false,
	"spriteSourceSize": {"x":0,"y":0,"w":16,"h":16},
	"sourceSize": {"w":16,"h":16}
},
"explosion/5/frame5.png":
{
	"frame": {"x":0,"y":376,"w":16,"h":16},
	"rotated": false,
	"trimmed": false,
	"spriteSourceSize": {"x":0,"y":0,"w":16,"h":16},
	"sourceSize": {"w":16,"h":16}
},
"explosion/5/frame6.png":
{
	"frame": {"x":0,"y":392,"w":16,"h":16},
	"rotated": false,
	"trimmed": false,
	"spriteSourceSize": {"x":0,"y":0,"w":16,"h":16},
	"sourceSize": {"w":16,"h":16}
},
"explosion/5/frame7.png":
{
	"frame": {"x":16,"y":408,"w":16,"h":16},
	"rotated": false,
	"trimmed": false,
	"spriteSourceSize": {"x":0,"y":0,"w":16,"h":16},
	"sourceSize": {"w":16,"h":16}
},
"explosion/5/frame8.png":
{
	"frame": {"x":16,"y":392,"w":16,"h":16},
	"rotated": false,
	"trimmed": false,
	"spriteSourceSize": {"x":0,"y":0,"w":16,"h":16},
	"sourceSize": {"w":16,"h":16}
},
"explosion/5/frame9.png":
{
	"frame": {"x":0,"y":408,"w":16,"h":16},
	"rotated": false,
	"trimmed": false,
	"spriteSourceSize": {"x":0,"y":0,"w":16,"h":16},
	"sourceSize": {"w":16,"h":16}
},
"explosion/6/frame1.png":
{
	"frame": {"x":16,"y":248,"w":16,"h":16},
	"rotated": false,
	"trimmed": false,
	"spriteSourceSize": {"x":0,"y":0,"w":16,"h":16},
	"sourceSize": {"w":16,"h":16}
},
"explosion/6/frame2.png":
{
	"frame": {"x":0,"y":232,"w":16,"h":16},
	"rotated": false,
	"trimmed": false,
	"spriteSourceSize": {"x":0,"y":0,"w":16,"h":16},
	"sourceSize": {"w":16,"h":16}
},
"explosion/6/frame3.png":
{
	"frame": {"x":16,"y":88,"w":16,"h":16},
	"rotated": false,
	"trimmed": false,
	"spriteSourceSize": {"x":0,"y":0,"w":16,"h":16},
	"sourceSize": {"w":16,"h":16}
},
"explosion/6/frame4.png":
{
	"frame": {"x":0,"y":88,"w":16,"h":16},
	"rotated": false,
	"trimmed": false,
	"spriteSourceSize": {"x":0,"y":0,"w":16,"h":16},
	"sourceSize": {"w":16,"h":16}
},
"explosion/6/frame5.png":
{
	"frame": {"x":16,"y":120,"w":16,"h":16},
	"rotated": false,
	"trimmed": false,
	"spriteSourceSize": {"x":0,"y":0,"w":16,"h":16},
	"sourceSize": {"w":16,"h":16}
},
"explosion/7/frame1.png":
{
	"frame": {"x":0,"y":120,"w":16,"h":16},
	"rotated": false,
	"trimmed": false,
	"spriteSourceSize": {"x":0,"y":0,"w":16,"h":16},
	"sourceSize": {"w":16,"h":16}
},
"explosion/7/frame2.png":
{
	"frame": {"x":0,"y":104,"w":16,"h":16},
	"rotated": false,
	"trimmed": false,
	"spriteSourceSize": {"x":0,"y":0,"w":16,"h":16},
	"sourceSize": {"w":16,"h":16}
},
"explosion/7/frame3.png":
{
	"frame": {"x":16,"y":72,"w":16,"h":16},
	"rotated": false,
	"trimmed": false,
	"spriteSourceSize": {"x":0,"y":0,"w":16,"h":16},
	"sourceSize": {"w":16,"h":16}
},
"explosion/7/frame4.png":
{
	"frame": {"x":8,"y":40,"w":16,"h":16},
	"rotated": false,
	"trimmed": false,
	"spriteSourceSize": {"x":0,"y":0,"w":16,"h":16},
	"sourceSize": {"w":16,"h":16}
},
"explosion/7/frame5.png":
{
	"frame": {"x":0,"y":56,"w":16,"h":16},
	"rotated": false,
	"trimmed": false,
	"spriteSourceSize": {"x":0,"y":0,"w":16,"h":16},
	"sourceSize": {"w":16,"h":16}
},
"explosion/8/frame1.png":
{
	"frame": {"x":12,"y":4,"w":4,"h":4},
	"rotated": false,
	"trimmed": false,
	"spriteSourceSize": {"x":0,"y":0,"w":4,"h":4},
	"sourceSize": {"w":4,"h":4}
},
"explosion/8/frame2.png":
{
	"frame": {"x":12,"y":0,"w":4,"h":4},
	"rotated": false,
	"trimmed": false,
	"spriteSourceSize": {"x":0,"y":0,"w":4,"h":4},
	"sourceSize": {"w":4,"h":4}
},
"explosion/8/frame3.png":
{
	"frame": {"x":8,"y":0,"w":4,"h":4},
	"rotated": false,
	"trimmed": false,
	"spriteSourceSize": {"x":0,"y":0,"w":4,"h":4},
	"sourceSize": {"w":4,"h":4}
},
"explosion/8/frame4.png":
{
	"frame": {"x":0,"y":0,"w":4,"h":4},
	"rotated": false,
	"trimmed": false,
	"spriteSourceSize": {"x":0,"y":0,"w":4,"h":4},
	"sourceSize": {"w":4,"h":4}
},
"explosion/8/frame5.png":
{
	"frame": {"x":8,"y":4,"w":4,"h":4},
	"rotated": false,
	"trimmed": false,
	"spriteSourceSize": {"x":0,"y":0,"w":4,"h":4},
	"sourceSize": {"w":4,"h":4}
},
"explosion/8/frame6.png":
{
	"frame": {"x":28,"y":4,"w":4,"h":4},
	"rotated": false,
	"trimmed": false,
	"spriteSourceSize": {"x":0,"y":0,"w":4,"h":4},
	"sourceSize": {"w":4,"h":4}
},
"explosion/8/frame7.png":
{
	"frame": {"x":24,"y":4,"w":4,"h":4},
	"rotated": false,
	"trimmed": false,
	"spriteSourceSize": {"x":0,"y":0,"w":4,"h":4},
	"sourceSize": {"w":4,"h":4}
},
"explosion/8/frame8.png":
{
	"frame": {"x":16,"y":4,"w":4,"h":4},
	"rotated": false,
	"trimmed": false,
	"spriteSourceSize": {"x":0,"y":0,"w":4,"h":4},
	"sourceSize": {"w":4,"h":4}
},
"explosion/8/frame9.png":
{
	"frame": {"x":20,"y":4,"w":4,"h":4},
	"rotated": false,
	"trimmed": false,
	"spriteSourceSize": {"x":0,"y":0,"w":4,"h":4},
	"sourceSize": {"w":4,"h":4}
},
"explosion/8/frame10.png":
{
	"frame": {"x":20,"y":0,"w":4,"h":4},
	"rotated": false,
	"trimmed": false,
	"spriteSourceSize": {"x":0,"y":0,"w":4,"h":4},
	"sourceSize": {"w":4,"h":4}
},
"explosion/8/frame11.png":
{
	"frame": {"x":28,"y":0,"w":4,"h":4},
	"rotated": false,
	"trimmed": false,
	"spriteSourceSize": {"x":0,"y":0,"w":4,"h":4},
	"sourceSize": {"w":4,"h":4}
},
"explosion/8/frame12.png":
{
	"frame": {"x":4,"y":4,"w":4,"h":4},
	"rotated": false,
	"trimmed": false,
	"spriteSourceSize": {"x":0,"y":0,"w":4,"h":4},
	"sourceSize": {"w":4,"h":4}
},
"explosion/8/frame13.png":
{
	"frame": {"x":0,"y":4,"w":4,"h":4},
	"rotated": false,
	"trimmed": false,
	"spriteSourceSize": {"x":0,"y":0,"w":4,"h":4},
	"sourceSize": {"w":4,"h":4}
},
"explosion/8/frame14.png":
{
	"frame": {"x":24,"y":0,"w":4,"h":4},
	"rotated": false,
	"trimmed": false,
	"spriteSourceSize": {"x":0,"y":0,"w":4,"h":4},
	"sourceSize": {"w":4,"h":4}
},
"explosion/8/frame15.png":
{
	"frame": {"x":16,"y":0,"w":4,"h":4},
	"rotated": false,
	"trimmed": false,
	"spriteSourceSize": {"x":0,"y":0,"w":4,"h":4},
	"sourceSize": {"w":4,"h":4}
},
"explosion/8/frame16.png":
{
	"frame": {"x":4,"y":0,"w":4,"h":4},
	"rotated": false,
	"trimmed": false,
	"spriteSourceSize": {"x":0,"y":0,"w":4,"h":4},
	"sourceSize": {"w":4,"h":4}
},
"explosion/9/frame1.png":
{
	"frame": {"x":0,"y":16,"w":8,"h":8},
	"rotated": false,
	"trimmed": false,
	"spriteSourceSize": {"x":0,"y":0,"w":8,"h":8},
	"sourceSize": {"w":8,"h":8}
},
"explosion/9/frame2.png":
{
	"frame": {"x":16,"y":16,"w":8,"h":8},
	"rotated": false,
	"trimmed": false,
	"spriteSourceSize": {"x":0,"y":0,"w":8,"h":8},
	"sourceSize": {"w":8,"h":8}
},
"explosion/9/frame3.png":
{
	"frame": {"x":16,"y":8,"w":8,"h":8},
	"rotated": false,
	"trimmed": false,
	"spriteSourceSize": {"x":0,"y":0,"w":8,"h":8},
	"sourceSize": {"w":8,"h":8}
},
"explosion/9/frame4.png":
{
	"frame": {"x":24,"y":8,"w":8,"h":8},
	"rotated": false,
	"trimmed": false,
	"spriteSourceSize": {"x":0,"y":0,"w":8,"h":8},
	"sourceSize": {"w":8,"h":8}
},
"trails/1/frames1.png":
{
	"frame": {"x":8,"y":8,"w":8,"h":8},
	"rotated": false,
	"trimmed": false,
	"spriteSourceSize": {"x":0,"y":0,"w":8,"h":8},
	"sourceSize": {"w":8,"h":8}
},
"trails/1/frames2.png":
{
	"frame": {"x":0,"y":8,"w":8,"h":8},
	"rotated": false,
	"trimmed": false,
	"spriteSourceSize": {"x":0,"y":0,"w":8,"h":8},
	"sourceSize": {"w":8,"h":8}
},
"trails/1/frames3.png":
{
	"frame": {"x":8,"y":16,"w":8,"h":8},
	"rotated": false,
	"trimmed": false,
	"spriteSourceSize": {"x":0,"y":0,"w":8,"h":8},
	"sourceSize": {"w":8,"h":8}
},
"trails/1/frames4.png":
{
	"frame": {"x":24,"y":16,"w":8,"h":8},
	"rotated": false,
	"trimmed": false,
	"spriteSourceSize": {"x":0,"y":0,"w":8,"h":8},
	"sourceSize": {"w":8,"h":8}
}},
"meta": {
	"app": "https://www.codeandweb.com/texturepacker",
	"version": "1.0",
	"image": "particles.png",
	"format": "RGBA8888",
	"size": {"w":32,"h":512},
	"scale": "1",
	"smartupdate": "$TexturePacker:SmartUpdate:17e8e67f6196052c4d1ccc24aaf06b12:1767916c40712e8ea2f990557ece70f9:767f0aa26e08023d62afa20c0c952bea$"
}
}
